buxcli/__init__.py
buxcli/intro.py
buxcli/mail.py
buxcli/main.py
buxcli/utils.py
buxcli-1.0.6.dist-info/licenses/LICENSE
buxcli-1.0.6.dist-info/METADATA
buxcli-1.0.6.dist-info/WHEEL
buxcli-1.0.6.dist-info/entry_points.txt
buxcli-1.0.6.dist-info/top_level.txt
buxcli-1.0.6.dist-info/RECORD
