Metadata-Version: 2.4
Name: buxcli
Version: 1.0.6
Summary: A simple CLI tool for alert you about your CLI.
Home-page: https://github.com/rushaad2911/buxcli
Author: Mohd. Rushaad Buxy
Author-email: m.rushaadq@gmail.com
Classifier: Programming Language :: Python :: 3
Classifier: License :: OSI Approved :: MIT License
Requires-Python: >=3.7
License-File: LICENSE
Requires-Dist: inquirer
Requires-Dist: rich
Requires-Dist: click
Requires-Dist: dotenv
Requires-Dist: setuptools
Dynamic: author
Dynamic: author-email
Dynamic: classifier
Dynamic: description
Dynamic: description-content-type
Dynamic: home-page
Dynamic: license-file
Dynamic: requires-dist
Dynamic: requires-python
Dynamic: summary
